oicana_native-0.1.0a2.dist-info/METADATA
oicana_native-0.1.0a2.dist-info/WHEEL
oicana_native-0.1.0a2.dist-info/licenses/LICENSE.md
oicana_native/__init__.py
oicana_native/oicana_native.pyd
oicana_native/py.typed
oicana_native-0.1.0a2.dist-info/RECORD
