Metadata-Version: 2.4
Name: oicana-native
Version: 0.1.0a2
Classifier: Development Status :: 3 - Alpha
Classifier: Intended Audience :: Developers
Classifier: Programming Language :: Python :: 3
Classifier: Programming Language :: Python :: 3.11
Classifier: Programming Language :: Python :: 3.12
Classifier: Programming Language :: Python :: 3.13
Classifier: Programming Language :: Python :: 3.14
Classifier: Programming Language :: Rust
Classifier: Topic :: Software Development :: Libraries :: Python Modules
License-File: LICENSE.md
License-File: LICENSE.md
Summary: Native Python bindings for Oicana (PDF templating with Typst)
Keywords: oicana,typst,typesetting,pdf
Home-Page: https://oicana.com
Author-email: Oicana <hello@oicana.com>
Requires-Python: >=3.11
Project-URL: Homepage, https://oicana.com
Project-URL: Repository, https://github.com/oicana/oicana
Project-URL: Documentation, https://docs.oicana.com
